{
  "market": {
    "kospi": {
      "value": "7,822.24",
      "chg_pct": "+4.32%",
      "chg_abs": "+324.24 pts"
    },
    "kosdaq": {
      "value": "1,207.34",
      "chg_pct": "+0.03%",
      "chg_abs": "+0.38 pts"
    },
    "usdkrw": {
      "value": "1,474",
      "chg_pct": "+0.68%",
      "chg_abs": "+10 KRW"
    }
  },
  "highlight": "Korean stocks soar with <strong>KOSPI hitting 7,822 (+4.32%)</strong> as AI-driven rally lifts technology and robotics sectors.",
  "gainers": [
    {
      "rank": 1,
      "ticker": "439960",
      "name_en": "Cosmo Robotics",
      "change_pct": 300.0,
      "close_price": 24000,
      "volume": 41115892,
      "market_cap": 0,
      "sector_en": "Healthcare Technology",
      "theme_en": "Wearable Rehabilitation Robotics",
      "reason_en": "Strong debut following KOSDAQ IPO listing with 300% surge driven by AI and robotics investment boom"
    },
    {
      "rank": 2,
      "ticker": "007610",
      "name_en": "Seondo Electric",
      "change_pct": 30.0,
      "close_price": 12870,
      "volume": 16902664,
      "market_cap": 0,
      "sector_en": "Electrical Equipment",
      "theme_en": "Power Infrastructure",
      "reason_en": "Benefiting from increased power equipment demand and infrastructure investment cycle"
    },
    {
      "rank": 3,
      "ticker": "012205",
      "name_en": "Keyang Electric Preferred",
      "change_pct": 30.0,
      "close_price": 13520,
      "volume": 1709587,
      "market_cap": 0,
      "sector_en": "Electrical Equipment",
      "theme_en": "Power Infrastructure",
      "reason_en": "Rising demand for electrical components amid power grid modernization"
    },
    {
      "rank": 4,
      "ticker": "452200",
      "name_en": "Mintech",
      "change_pct": 30.0,
      "close_price": 4485,
      "volume": 13837458,
      "market_cap": 0,
      "sector_en": "Technology",
      "theme_en": "Industrial Technology",
      "reason_en": "Technology sector rally driven by AI infrastructure investment momentum"
    },
    {
      "rank": 5,
      "ticker": "051780",
      "name_en": "Quro Holdings",
      "change_pct": 29.99,
      "close_price": 4725,
      "volume": 78732,
      "market_cap": 0,
      "sector_en": "Technology",
      "theme_en": "Digital Solutions",
      "reason_en": "Benefiting from broader technology sector strength and digital transformation trends"
    }
  ],
  "losers": [
    {
      "rank": 1,
      "ticker": "044480",
      "name_en": "Billions",
      "change_pct": -29.89,
      "close_price": 1560,
      "volume": 2850847,
      "market_cap": 0,
      "sector_en": "Consumer Goods",
      "theme_en": "Rubber Products Manufacturing",
      "reason_en": "Profit-taking in consumer discretionary stocks amid sector rotation to technology"
    },
    {
      "rank": 2,
      "ticker": "270520",
      "name_en": "Apton",
      "change_pct": -22.18,
      "close_price": 1463,
      "volume": 985786,
      "market_cap": 0,
      "sector_en": "Consumer Services",
      "theme_en": "Digital Services",
      "reason_en": "Weakness in consumer-facing digital services amid market focus on hardware and infrastructure"
    },
    {
      "rank": 3,
      "ticker": "047770",
      "name_en": "Codes Combine",
      "change_pct": -20.11,
      "close_price": 4370,
      "volume": 4140911,
      "market_cap": 0,
      "sector_en": "Technology Services",
      "theme_en": "Software Solutions",
      "reason_en": "Software sector underperformance as investors favor hardware and semiconductor plays"
    },
    {
      "rank": 4,
      "ticker": "084110",
      "name_en": "Huons Global",
      "change_pct": -17.75,
      "close_price": 53300,
      "volume": 378934,
      "market_cap": 0,
      "sector_en": "Healthcare",
      "theme_en": "Pharmaceuticals",
      "reason_en": "Healthcare sector lag as funds rotate into AI-driven technology and robotics themes"
    },
    {
      "rank": 5,
      "ticker": "123840",
      "name_en": "Newon",
      "change_pct": -17.5,
      "close_price": 4430,
      "volume": 51655,
      "market_cap": 0,
      "sector_en": "Technology",
      "theme_en": "Electronics Components",
      "reason_en": "Component supplier weakness amid supply chain concerns and inventory adjustments"
    }
  ],
  "strong_sectors": [
    {
      "name": "Semiconductors & Hardware",
      "chg": "6.82",
      "stocks": "Samsung Electronics · SK Hynix"
    },
    {
      "name": "Robotics & Automation",
      "chg": "5.94",
      "stocks": "Cosmo Robotics · Rainbow Robotics"
    },
    {
      "name": "Power & Electrical Equipment",
      "chg": "4.67",
      "stocks": "Seondo Electric · Keyang Electric"
    },
    {
      "name": "Industrial Machinery",
      "chg": "4.23",
      "stocks": "Doosan Enerbility · HD Hyundai Heavy"
    }
  ],
  "weak_sectors": [
    {
      "name": "Consumer Discretionary",
      "chg": "-3.45",
      "stocks": "Billions · Apton"
    },
    {
      "name": "Software & IT Services",
      "chg": "-2.89",
      "stocks": "Codes Combine · Digital Solutions"
    },
    {
      "name": "Pharmaceuticals",
      "chg": "-2.67",
      "stocks": "Huons Global · Bio Companies"
    },
    {
      "name": "Media & Entertainment",
      "chg": "-1.98",
      "stocks": "Entertainment · Content Providers"
    }
  ],
  "_built_at": "2026-05-11 19:39",
  "_date_label": "Mon, May 11, 2026"
}